sphinx_dust/__init__.py
sphinx_dust/directive.py
sphinx_dust-1.2.5.dist-info/licenses/LICENSE.txt
sphinx_dust-1.2.5.dist-info/METADATA
sphinx_dust-1.2.5.dist-info/WHEEL
sphinx_dust-1.2.5.dist-info/top_level.txt
sphinx_dust-1.2.5.dist-info/RECORD
