Metadata-Version: 2.4
Name: sphinx-dust
Version: 1.2.5
Summary: Sphinx extension to produce warnings when a doc needs proofreading.
Home-page: https://github.com/Polyconseil/sphinx-dust
Author: Polyconseil
Author-email: opensource+sphinx-dust@polyconseil.fr
License: BSD
Keywords: sphinx documentation review proofread up-to-date
Classifier: Development Status :: 3 - Alpha
Classifier: Environment :: Plugins
Classifier: Framework :: Sphinx :: Extension
Classifier: Intended Audience :: Developers
Classifier: License :: OSI Approved :: BSD License
Classifier: Natural Language :: English
Classifier: Programming Language :: Python
License-File: LICENSE.txt
Requires-Dist: Sphinx>=1.2
Dynamic: author
Dynamic: author-email
Dynamic: classifier
Dynamic: description
Dynamic: home-page
Dynamic: keywords
Dynamic: license
Dynamic: license-file
Dynamic: requires-dist
Dynamic: summary
